[{"name": "Saskatoon Urology Associates", "address": "210 Avenue P S #410, Saskatoon, SK S7M 2W2", "city": "Saskatoon", "state": "Saskatchewan", "state_code": "", "phone": "+1 306-653-3255", "website": "http://www.saskurology.ca/", "rating": 3.7, "reviews": 21, "place_id": "ChIJFZeetNH2BFMRYBSXkFdRyMU", "latitude": 52.1270465, "longitude": -106.6935559, "subtypes": "Urology clinic"}, {"name": "Dr. Gerrit Van Wyk", "address": "550 Main St N, Moose Jaw, SK S6H 4P2", "city": "Moose Jaw", "state": "Saskatchewan", "state_code": "", "phone": "", "website": "", "rating": 2, "reviews": 4, "place_id": "ChIJC71neS_cG1MRa0vVJ9LPlB8", "latitude": 50.3951287, "longitude": -105.5351507, "subtypes": "Urologist"}]